eason_mcp_test/__init__.py
eason_mcp_test-1.0.0.dist-info/WHEEL
eason_mcp_test-1.0.0.dist-info/entry_points.txt
eason_mcp_test-1.0.0.dist-info/METADATA
eason_mcp_test-1.0.0.dist-info/RECORD
