Metadata-Version: 2.3
Name: eason-mcp-test
Version: 1.0.0
Summary: add calculator
Author: Yichen Yao
Author-email: Yichen Yao <eason.yyc@inftech.ai>
Requires-Dist: mcp[cli]>=1.12.4
Requires-Python: >=3.13
